dopey/__init__.py
dopey/__main__.py
dopey/dopey.py
dopey-1.0.1.dist-info/LICENSE
dopey-1.0.1.dist-info/METADATA
dopey-1.0.1.dist-info/WHEEL
dopey-1.0.1.dist-info/entry_points.txt
dopey-1.0.1.dist-info/top_level.txt
dopey-1.0.1.dist-info/RECORD
