Metadata-Version: 2.1
Name: dopey
Version: 1.0.1
Summary: A brainfuck interpreter made using python.
Home-page: https://github.com/gio101046/dopey
Author: Giovani Rodriguez
Author-email: me@grodriguez.dev
License: MIT
Platform: UNKNOWN
Classifier: License :: OSI Approved :: MIT License
Classifier: Programming Language :: Python :: 3
Classifier: Programming Language :: Python :: 3.9
